{
  "screen_number": 4,
  "voiceover_text": "Collaborate in real-time with built-in chat, file sharing, and instant task assignments.",
  "target_duration_sec": 7,
  "screen_type": "screencast",
  "on_screen_visual_keywords": "team chat window, file upload, assigning tasks",
  "action_notes": "Cursor demonstrates sending a message, uploading a file, and assigning a task",
  "image_url": "https://www.computerworld.com/wp-content/uploads/2025/05/2094202-0-94321200-1747638870-google-spaces-chat-window2.jpg?quality=50&strip=all&w=1024"
}